coentice_datasources/__init__.py
coentice_datasources/client/__init__.py
coentice_datasources/client/api_client.py
coentice_datasources/core/__init__.py
coentice_datasources/core/datasources.py
coentice_datasources-0.1.0.dist-info/METADATA
coentice_datasources-0.1.0.dist-info/WHEEL
coentice_datasources-0.1.0.dist-info/top_level.txt
coentice_datasources-0.1.0.dist-info/RECORD
