Metadata-Version: 2.4
Name: coentice_datasources
Version: 0.1.0
Summary: A package for managing datasource templates in Coentice Integration
Author: Kartik Patel
Author-email: kartik@prowesolution.com
Requires-Dist: requests
Dynamic: author
Dynamic: author-email
Dynamic: requires-dist
Dynamic: summary
